fastinit/__init__.py
fastinit/cli.py
fastinit_cli-0.1.4.dist-info/METADATA
fastinit_cli-0.1.4.dist-info/WHEEL
fastinit_cli-0.1.4.dist-info/entry_points.txt
fastinit_cli-0.1.4.dist-info/top_level.txt
fastinit_cli-0.1.4.dist-info/RECORD
