Metadata-Version: 2.4
Name: fastinit-cli
Version: 0.1.4
Summary: A simple CLI to quickly and cleanly create FastAPI projects and modules.
Author-email: João Pedro de Oliveira Matos <joaopedrooliveira030506@gmail.com>
Requires-Python: >=3.8
